infusevideo_cli/__init__.py
infusevideo_cli/__main__.py
infusevideo_cli-0.3.0.dist-info/LICENSE
infusevideo_cli-0.3.0.dist-info/METADATA
infusevideo_cli-0.3.0.dist-info/WHEEL
infusevideo_cli-0.3.0.dist-info/entry_points.txt
infusevideo_cli-0.3.0.dist-info/top_level.txt
infusevideo_cli-0.3.0.dist-info/RECORD
