Metadata-Version: 2.1
Name: infusevideo-cli
Version: 0.3.0
Summary: Command-line utility to interact with the Infuse Video API
Home-page: https://www.infuse.video
Author: Infuse Video
Author-email: support@infuse.video
License: MIT
Classifier: Development Status :: 3 - Alpha
Classifier: Environment :: Console
Classifier: Intended Audience :: Developers
Classifier: License :: OSI Approved :: MIT License
Classifier: Operating System :: OS Independent
Classifier: Programming Language :: Python :: 3.9
Classifier: Programming Language :: Python :: 3.10
Classifier: Topic :: Multimedia :: Video
Requires-Python: >=3.9
License-File: LICENSE
Requires-Dist: docopt ==0.6.2
Requires-Dist: pydantic <2,>=1.9.0
Requires-Dist: infusevideo-sdk >=0.3.0
